CHANGELOG.txt
MANIFEST.in
README.txt
setup.py
Lightbox.egg-info/PKG-INFO
Lightbox.egg-info/SOURCES.txt
Lightbox.egg-info/dependency_links.txt
Lightbox.egg-info/entry_points.txt
Lightbox.egg-info/not-zip-safe
Lightbox.egg-info/paster_plugins.txt
Lightbox.egg-info/requires.txt
Lightbox.egg-info/top_level.txt
lightbox/__init__.py
lightbox/release.py
lightbox/widgets.py
lightbox/static/css/lightbox.css
lightbox/static/images/blank.gif
lightbox/static/images/bullet.gif
lightbox/static/images/close.gif
lightbox/static/images/closelabel.gif
lightbox/static/images/donate-button.gif
lightbox/static/images/download-icon.gif
lightbox/static/images/image-1.jpg
lightbox/static/images/image-3.jpg
lightbox/static/images/image-4.jpg
lightbox/static/images/loading.gif
lightbox/static/images/next.gif
lightbox/static/images/nextlabel.gif
lightbox/static/images/prev.gif
lightbox/static/images/prevlabel.gif
lightbox/static/images/thumb-1.jpg
lightbox/static/images/thumb-3.jpg
lightbox/static/images/thumb-4.jpg
lightbox/static/javascript/lightbox.js
lightbox/templates/__init__.py
