Metadata-Version: 1.0
Name: Lightbox
Version: 2.1
Summary: Lightbox photo display widget
Home-page: http://docs.turbogears.org/tgLightbox
Author: Lokesh Dhakar, Kevin Dangoor, Christopher Arndt
Author-email: dangoor+lightbox@gmail.com
License: MIT
Download-URL: http://pypi.python.org/pypi/Lightbox
Keywords: turbogears.widgets
Platform: UNKNOWN
Classifier: Development Status :: 4 - Beta
Classifier: Operating System :: OS Independent
Classifier: Programming Language :: Python
Classifier: Topic :: Software Development :: Libraries :: Python Modules
Classifier: Framework :: TurboGears
Classifier: Framework :: TurboGears :: Widgets
